gp_pax_terminal_downloader/__init__.py
gp_pax_terminal_downloader/__main__.py
gp_pax_terminal_downloader/functions.py
gp_pax_terminal_downloader/mysql_helper.py
gp_pax_terminal_downloader-0.1.6.dist-info/LICENSE
gp_pax_terminal_downloader-0.1.6.dist-info/METADATA
gp_pax_terminal_downloader-0.1.6.dist-info/WHEEL
gp_pax_terminal_downloader-0.1.6.dist-info/top_level.txt
gp_pax_terminal_downloader-0.1.6.dist-info/RECORD
