Metadata-Version: 2.1
Name: gp-pax-terminal-downloader
Version: 0.1.6
Summary: Green Pay Paxstore Terminals downloader
Home-page: https://www.greenpayci.com
Requires-Dist: requests
Requires-Dist: progress
Requires-Dist: progressbar
Requires-Dist: mysql-connector-python
Requires-Dist: paxstore-open-api-sdk
